<?xml version="1.0" encoding="UTF-8"?>
<Patch>
  <Operation Class="PatchOperationConditional">
    <xpath>/Defs/HediffDef[defName="HearingLoss"]/comps</xpath>
    <nomatch Class="PatchOperationAdd">
      <xpath>/Defs/HediffDef[defName="HearingLoss"]</xpath>
      <value>
        <comps></comps>
      </value>
    </nomatch>
  </Operation>
  <Operation Class="PatchOperationAdd">
    <xpath>/Defs/HediffDef[defName="HearingLoss"]/comps</xpath>
    <value>
      <li Class="MoreInjuries.HealthConditions.Secondary.HediffCompProperties_CausedBy"></li>
    </value>
  </Operation>
</Patch>