<?xml version="1.0" encoding="utf-8"?>
<Defs>
  <RecipeDef>
    <defName>Make_Thoracoscope</defName>
    <label>make thoracoscope</label>
    <description>Make a thoracoscope.</description>
    <jobString>Making a thoracoscope.</jobString>
    <workAmount>1000</workAmount>
    <effectWorking>Cook</effectWorking>
    <soundWorking>Recipe_Machining</soundWorking>
    <allowMixingIngredients>true</allowMixingIngredients>
    <researchPrerequisites>
      <li>AdvancedThoracicSurgery</li>
    </researchPrerequisites>
    <ingredients>
      <li>
        <filter>
          <thingDefs>
            <li>Steel</li>
          </thingDefs>
        </filter>
        <count>20</count>
      </li>
      <li>
        <filter>
          <thingDefs>
            <li>Chemfuel</li>
          </thingDefs>
        </filter>
        <count>20</count>
      </li>
      <li>
        <filter>
          <thingDefs>
            <li>ComponentIndustrial</li>
          </thingDefs>
        </filter>
        <count>4</count>
      </li>
      <li>
        <filter>
          <thingDefs>
            <li>Plasteel</li>
          </thingDefs>
        </filter>
        <count>50</count>
      </li>
      <li>
        <filter>
          <thingDefs>
            <li>Gold</li>
          </thingDefs>
        </filter>
        <count>2</count>
      </li>
      <li>
        <filter>
          <thingDefs>
            <li>Silver</li>
          </thingDefs>
        </filter>
        <count>25</count>
      </li>
    </ingredients>
    <products>
      <Thoracoscope>1</Thoracoscope>
    </products>
    <fixedIngredientFilter>
      <thingDefs>
        <li>Steel</li>
        <li>Chemfuel</li>
        <li>ComponentIndustrial</li>
        <li>Plasteel</li>
        <li>Gold</li>
        <li>Silver</li>
      </thingDefs>
    </fixedIngredientFilter>
    <recipeUsers>
      <li>TableMachining</li>
    </recipeUsers>
    <skillRequirements>
      <Crafting>8</Crafting>
    </skillRequirements>
    <workSkill>Intellectual</workSkill>
    <workSpeedStat>DrugSynthesisSpeed</workSpeedStat>
  </RecipeDef>
</Defs>